veclite/__init__.py
veclite/__version__.py
veclite/py.typed
veclite/clients/__init__.py
veclite/core/__init__.py
veclite/core/async_client.py
veclite/core/base_client.py
veclite/core/client.py
veclite/core/context.py
veclite/core/errors.py
veclite/core/results.py
veclite/embeddings/__init__.py
veclite/embeddings/cache.py
veclite/embeddings/providers/__init__.py
veclite/embeddings/providers/base.py
veclite/embeddings/providers/voyage_async.py
veclite/embeddings/providers/voyage_base.py
veclite/embeddings/providers/voyage_sync.py
veclite/query/__init__.py
veclite/query/binder.py
veclite/query/builder.py
veclite/query/builder_sync.py
veclite/query/hybrid.py
veclite/query/ir.py
veclite/query/planner.py
veclite/query/sqlgen.py
veclite/query/validation.py
veclite/query/compiler/__init__.py
veclite/query/compiler/delete.py
veclite/query/compiler/insert.py
veclite/query/compiler/mixins.py
veclite/query/compiler/select.py
veclite/query/compiler/update.py
veclite/query/compiler/upsert.py
veclite/query/compiler_sync/__init__.py
veclite/query/compiler_sync/delete.py
veclite/query/compiler_sync/insert.py
veclite/query/compiler_sync/select.py
veclite/query/compiler_sync/update.py
veclite/query/compiler_sync/upsert.py
veclite/query/dialect/__init__.py
veclite/query/dialect/sqlite.py
veclite/query/mixins/__init__.py
veclite/query/mixins/filter_mixin.py
veclite/query/mixins/order_limit_mixin.py
veclite/query/mixins/selection_mixin.py
veclite/schema/__init__.py
veclite/schema/builder.py
veclite/schema/fields.py
veclite/schema/schema.py
veclite/schema/table.py
veclite/schema/vector_config.py
veclite/schema/view.py
veclite/utils/__init__.py
veclite/utils/voyage_limits.py
veclite/utils/rate_limiters/__init__.py
veclite/utils/rate_limiters/request_limiter.py
veclite/utils/rate_limiters/token_limiter.py
veclite/vector/__init__.py
veclite/vector/store.py
veclite-0.1.0.dist-info/licenses/LICENSE
veclite-0.1.0.dist-info/METADATA
veclite-0.1.0.dist-info/WHEEL
veclite-0.1.0.dist-info/top_level.txt
veclite-0.1.0.dist-info/RECORD
