Metadata-Version: 2.4
Name: veclite
Version: 0.1.0
Summary: A schema-first SQLite ORM with built-in vector embeddings and hybrid search
Author-email: Lucas Astorian <your.email@example.com>
Maintainer-email: Lucas Astorian <your.email@example.com>
License: MIT
Project-URL: Homepage, https://github.com/yourusername/veclite
Project-URL: Documentation, https://github.com/yourusername/veclite#readme
Project-URL: Repository, https://github.com/yourusername/veclite
Project-URL: Issues, https://github.com/yourusername/veclite/issues
Project-URL: Changelog, https://github.com/yourusername/veclite/blob/main/CHANGELOG.md
Keywords: sqlite,orm,vector-database,embeddings,semantic-search,hybrid-search,rag,vector-search
Classifier: Development Status :: 3 - Alpha
Classifier: Intended Audience :: Developers
Classifier: License :: OSI Approved :: MIT License
Classifier: Programming Language :: Python :: 3
Classifier: Programming Language :: Python :: 3.9
Classifier: Programming Language :: Python :: 3.10
Classifier: Programming Language :: Python :: 3.11
Classifier: Programming Language :: Python :: 3.12
Classifier: Topic :: Database
Classifier: Topic :: Software Development :: Libraries :: Python Modules
Classifier: Topic :: Scientific/Engineering :: Artificial Intelligence
Requires-Python: >=3.9
License-File: LICENSE
Requires-Dist: numpy>=1.20.0
Requires-Dist: lmdb>=1.3.0
Provides-Extra: voyage
Requires-Dist: voyageai>=0.2.0; extra == "voyage"
Requires-Dist: tenacity>=8.0.0; extra == "voyage"
Provides-Extra: all
Requires-Dist: voyageai>=0.2.0; extra == "all"
Requires-Dist: tenacity>=8.0.0; extra == "all"
Provides-Extra: dev
Requires-Dist: pytest>=7.0.0; extra == "dev"
Requires-Dist: pytest-asyncio>=0.21.0; extra == "dev"
Requires-Dist: black>=23.0.0; extra == "dev"
Requires-Dist: ruff>=0.1.0; extra == "dev"
Requires-Dist: mypy>=1.0.0; extra == "dev"
Dynamic: license-file
